{"_id": "bash", "name": "Bash", "type": "programming"}
{"_id": "c", "name": "C", "type": "programming"}
{"_id": "c_sharp", "name": "C#", "type": "programming"}
{"_id": "java", "name": "Java", "type": "programming"}
{"_id": "javascript", "name": "JavaScript", "type": "programming"}
{"_id": "mumps", "name": "MUMPS", "type": "programming"}
{"_id": "php", "name": "PHP", "type": "programming"}
{"_id": "python", "name": "Python", "type": "programming"}
{"_id": "ruby", "name": "Ruby", "type": "programming"}
{"_id": "typescript", "name": "TypeScript", "type": "programming"}
{"_id": "vbscript", "name": "VBScript", "type": "programming"}
{"_id": "vimscript", "name": "Vimscript", "type": "programming"}

{"_id": "css", "name": "CSS", "type": "other"}
{"_id": "html", "name": "HTML", "type": "other"}
{"_id": "sass", "name": "Sass", "type": "other"}
{"_id": "sql", "name": "SQL", "type": "other"}
{"_id": "yaml", "name": "YAML", "type": "other"}
